README.rst
savefig.py
setup.py
savefig.egg-info/PKG-INFO
savefig.egg-info/SOURCES.txt
savefig.egg-info/dependency_links.txt
savefig.egg-info/requires.txt
savefig.egg-info/top_level.txt