Metadata-Version: 1.1
Name: savefig
Version: 0.0.3
Summary: Save matplotlib figures with embedded metadata for reproducibility and profit
Home-page: https://github.com/dfm/savefig
Author: Daniel Foreman-Mackey
Author-email: dan@dfm.io
License: MIT
Platform: UNKNOWN
Classifier: Intended Audience :: Developers
Classifier: Intended Audience :: Science/Research
Classifier: License :: OSI Approved :: MIT License
Classifier: Operating System :: OS Independent
Classifier: Programming Language :: Python
